libname/__init__.py
libname/search_sort_array_algo.py
search_sort_array_algo-0.0.1.dist-info/METADATA
search_sort_array_algo-0.0.1.dist-info/WHEEL
search_sort_array_algo-0.0.1.dist-info/top_level.txt
search_sort_array_algo-0.0.1.dist-info/RECORD
